linearpartition.cpython-37m-x86_64-linux-gnu.so
linearpartition_unofficial-0.3.dist-info/WHEEL
linearpartition_unofficial-0.3.dist-info/METADATA
linearpartition_unofficial-0.3.dist-info/top_level.txt
linearpartition_unofficial-0.3.dist-info/RECORD
linearpartition_unofficial-0.3.dist-info/LICENSE
