Metadata-Version: 2.1
Name: linearpartition-unofficial
Version: 0.3
Summary: Python interface to LinearPartition, a linear-time RNA secondary structure prediction tool
Home-page: https://github.com/ChangLabSNU/python-linearpartition
Download-URL: https://github.com/ChangLabSNU/python-linearpartition/releases
Author: Hyeshik Chang
Author-email: hyeshik@snu.ac.kr
License: MIT
Keywords: RNA,secondary structure,RNA structure
Classifier: Development Status :: 3 - Alpha
Classifier: Environment :: Plugins
Classifier: Intended Audience :: Science/Research
Classifier: License :: OSI Approved :: MIT License
Classifier: Operating System :: POSIX
Classifier: Programming Language :: Python
Classifier: Topic :: Scientific/Engineering :: Bio-Informatics
License-File: LICENSE
Requires-Dist: numpy
